LICENSE
README.md
setup.cfg
setup.py
Topsis_Sukhnoor_102003112/Topsis_Sukhnoor_102003112.py
Topsis_Sukhnoor_102003112.egg-info/PKG-INFO
Topsis_Sukhnoor_102003112.egg-info/SOURCES.txt
Topsis_Sukhnoor_102003112.egg-info/dependency_links.txt
Topsis_Sukhnoor_102003112.egg-info/entry_points.txt
Topsis_Sukhnoor_102003112.egg-info/requires.txt
Topsis_Sukhnoor_102003112.egg-info/top_level.txt