Metadata-Version: 2.1
Name: Topsis-Sukhnoor-102003112
Version: 1.0.1
Summary: This is a Python library created for handling problems related to Multiple Criteria Decision Making(MCDM)
Home-page: https://github.com/sukhnoor21/Topsis-Sukhnoor_102003112
Author: Sukhnoor Kaur
Author-email: sukhnoorkaur21@gmail.com
License: MIT
Platform: UNKNOWN
Classifier: License :: OSI Approved :: MIT License
Classifier: Programming Language :: Python :: 3.6
Classifier: Programming Language :: Python :: 3.7
Classifier: Programming Language :: Python :: 3.8
License-File: LICENSE
